Workbook

Sheet Read me
B2: Janitorial bid pricing worksheet
B3: Rosebud Solutions
B5: How to use this
B6: Fill in every yellow cell. Yellow means you type it. Everything else calculates.
B7: Work through the tabs in order: 1 Site, 2 Labor, 3 Costs, 4 Periodic, 5 The bid.
B8: The bid price appears on tab 5. Nothing else needs to be worked out by hand.
B10: The two things bids get wrong
B11: 1. Quoting off the base wage instead of the fully loaded rate. Tab 2 loads it for you.
B12: 2. Adding a margin percentage on top of cost. That does not give you that margin.
B13: Tab 5 divides by (1 - margin), which does. A 30% target on $1,000 of cost is $1,429, not $1,300.
B15: Production rates
B16: The ISSA 612 cleaning times standard is the industry benchmark.
... B27: (c) Rosebud Global Ltd. You may use and adapt this workbook for your own business.

Sheet 1 Site
B2: Site details
B3: Yellow cells are yours to fill in.
B5: Prospect
B6: Contact and title
B7: Premises address
B8: Walkthrough date
B9: Bid due date
B10: Facility type
B11: Restroom count
B12: Fixture count
B13: Floor types
B14: Furniture density
... B21: This sheet is deliberately blank. It is the one tab that reaches a client if the file is forwarded.

Sheet 2 Labor
B2: Labor hours and loaded rate
B3: Cleanable sq ft divided by production rate equals hours per visit.
B5: Area type | C5: Cleanable sq ft | D5: Production rate (sq ft/hr) | E5: Hours per visit
B6: Open office | C6: 6000 | D6: 3500 | E6: =IF(D6=0,0,C6/D6) -> 1.7142857
B7: Private offices | C7: 2000 | D7: 2800 | E7: =IF(D7=0,0,C7/D7) -> 0.71428571
B8: Restrooms | C8: 600 | D8: 500 | E8: =IF(D8=0,0,C8/D8) -> 1.2
B9: Kitchen / break area | C9: 500 | D9: 2000 | E9: =IF(D9=0,0,C9/D9) -> 0.25
B10: Corridors and stairs | C10: 900 | D10: 4000 | E10: =IF(D10=0,0,C10/D10) -> 0.225
B11: Entrance and lobby | C11: 600 | D11: 3500 | E11: =IF(D11=0,0,C11/D11) -> 0.17142857
B12: Warehouse / production | C12: 0 | D12: 0 | E12: =IF(D12=0,0,C12/D12) -> 0
B13: Total | C13: =SUM(C6:C12) -> 10600 | E13: =SUM(E6:E12) -> 4.275
B14: Zero production rate excludes the row. Example values shown, overwrite them.
B16: Fully loaded hourly rate
B17: Base hourly wage | C17: 16
B18: Payroll taxes (% of wage) | C18: 0.0765
B19: Workers' compensation (% of wage) | C19: 0.05
B20: General liability allocation (% of wage) | C20: 0.02
B21: Fully loaded hourly rate | C21: =C17*(1+C18+C19+C20) -> 18.344
B22: Quote from this rate, never the base wage.
B24: Monthly labor
B25: Hours per visit | C25: ='2 Labor'!$E$13 -> 4.275
B26: Visits per month | C26: 21
B27: Total hours per month | C27: ='2 Labor'!$E$13*'2 Labor'!$C$26 -> 89.775
B28: Monthly labor cost | C28: ='2 Labor'!$C$27*'2 Labor'!$C$21 -> 1646.8326
B30: 21 visits per month is five nights a week. Change it to match the schedule.

Sheet 3 Costs
B2: The costs most bids forget
B3: Every one of these is a real monthly cost. Leaving one out comes off your margin.
B5: Cost | C5: Monthly | D5: Note
B6: Drive time | C6: =C18 -> 192.612 | D6: Pulled from the helper below. Round trip hours x visits x loaded rate.
B7: Vehicle and fuel | C7: 60
B8: Supervision and quality inspection | C8: 120 | D8: Someone checks the work and takes the client's calls.
B9: Cleaning chemicals | C9: 55
B10: Consumables billed to you | C10: 85 | D10: Liners and paper add up faster than chemicals.
B11: Equipment depreciation or rental | C11: 40
B12: Uniforms and PPE | C12: 20
B13: Overhead allocation | C13: 100 | D13: Admin, insurance, software, share of premises.
B14: Total additional monthly cost | C14: =SUM(C6:C13) -> 672.612
B16: Drive time helper
B17: Round trip hours per visit | C17: 0.5
B18: Drive time cost per month | C18: =C17*'2 Labor'!$C$26*'2 Labor'!$C$21 -> 192.612
B19: This feeds the drive time row above automatically. Set the round trip hours and it flows through.

Sheet 4 Periodic
B2: Periodic and specialist work
B3: Price separately. Only fold into the monthly figure if the client requires an all-in number.
B5: Task | C5: Times per year | D5: Hours | E5: Hourly rate | F5: Annual cost | G5: Monthly amortised
B6: Strip and wax hard floors | C6: 0 | D6: 0 | E6: 0 | F6: =C6*D6*E6 -> 0 | G6: =F6/12 -> 0
B7: Machine scrub / burnish | C7: 0 | D7: 0 | E7: 0 | F7: =C7*D7*E7 -> 0 | G7: =F7/12 -> 0
B8: Carpet extraction | C8: 0 | D8: 0 | E8: 0 | F8: =C8*D8*E8 -> 0 | G8: =F8/12 -> 0
B9: Interior window cleaning | C9: 0 | D9: 0 | E9: 0 | F9: =C9*D9*E9 -> 0 | G9: =F9/12 -> 0
B10: Exterior window cleaning | C10: 0 | D10: 0 | E10: 0 | F10: =C10*D10*E10 -> 0 | G10: =F10/12 -> 0
B11: Upholstery cleaning | C11: 0 | D11: 0 | E11: 0 | F11: =C11*D11*E11 -> 0 | G11: =F11/12 -> 0
B12: High dusting | C12: 0 | D12: 0 | E12: 0 | F12: =C12*D12*E12 -> 0 | G12: =F12/12 -> 0
B13: Pressure washing | C13: 0 | D13: 0 | E13: 0 | F13: =C13*D13*E13 -> 0 | G13: =F13/12 -> 0
B14: Total | F14: =SUM(F6:F13) -> 0 | G14: =SUM(G6:G13) -> 0

Sheet 5 The bid
B2: The bid
B3: Everything here calculates. The only cell to set is your target margin.
B5: Monthly labor cost | C5: ='2 Labor'!$C$28 -> 1646.8326
B6: Total additional monthly cost | C6: ='3 Costs'!$C$14 -> 672.612
B7: Periodic work, monthly amortised | C7: ='4 Periodic'!$G$14 -> 0
B8: Total monthly cost | C8: =SUM(C5:C7) -> 2319.4446
B9: Target margin | C9: 0.35
B10: MONTHLY BID PRICE | C10: =IF($C$9>=1,0,$C$8/(1-$C$9)) -> 3568.3763 | D10: Cost divided by (1 minus margin). Adding a percentage on top does not give you that margin.
B13: Sense check
B14: Check | C14: Value | D14: What good looks like
B15: Price per cleanable sq ft per month | C15: =IF('2 Labor'!$C$13=0,0,$C$10/'2 Labor'!$C$13) -> 0.33663927 | D15: Reported so you can compare against your own accounts. It scales with frequency, so a five-night building reads far higher than a three-night one. There is no single right number.
B16: Price per visit | C16: =IF('2 Labor'!$C$26=0,0,$C$10/'2 Labor'!$C$26) -> 169.92268
B17: Effective hourly revenue | C17: =IF('2 Labor'!$C$27=0,0,$C$10/'2 Labor'!$C$27) -> 39.747996 | D17: The check that travels. Aim for roughly 2 to 3 times your fully loaded rate on tab 2. Below 2x, the overhead and margin are not really in the price.
B18: Break-even monthly price | C18: =$C$8 -> 2319.4446 | D18: Never bid below this.
B19: Gross margin at bid price | C19: =IF($C$10=0,0,($C$10-$C$8)/$C$10) -> 0.35
B22: Walk away if
B23: The price needed to win is below your break-even.
B24: The service window is too tight to staff reliably.
B25: The specification needs equipment you would buy for this job alone.
B26: The incumbent has held it three cycles with no complaint on record.
